onnx/__init__.py
onnx/onnx_bench.py
onnx/onnx_export.py
onnx/temp_model.py
soco_encoders/LoggingHandler.py
soco_encoders/SentenceTransformer.py
soco_encoders/Tokenizer.py
soco_encoders/__init__.py
soco_encoders/cloud_bucket.py
soco_encoders/data_samplers.py
soco_encoders/datasets.py
soco_encoders/encoders.py
soco_encoders/model_loaders.py
soco_encoders/util.py
soco_encoders/evaluation/BinaryEmbeddingSimilarityEvaluator.py
soco_encoders/evaluation/EmbeddingSimilarityEvaluator.py
soco_encoders/evaluation/LabelAccuracyEvaluator.py
soco_encoders/evaluation/SentenceEvaluator.py
soco_encoders/evaluation/SequentialEvaluator.py
soco_encoders/evaluation/SimilarityFunction.py
soco_encoders/evaluation/TripletEvaluator.py
soco_encoders/evaluation/__init__.py
soco_encoders/losses/BatchHardTripletLoss.py
soco_encoders/losses/CosineSimilarityLoss.py
soco_encoders/losses/MultipleNegativesRankingLoss.py
soco_encoders/losses/SoftmaxLoss.py
soco_encoders/losses/TripletLoss.py
soco_encoders/losses/__init__.py
soco_encoders/losses/test_batch_hard_triplet_loss.py
soco_encoders/models/ALBERT.py
soco_encoders/models/BERT.py
soco_encoders/models/BoW.py
soco_encoders/models/CNN.py
soco_encoders/models/Dense.py
soco_encoders/models/LSTM.py
soco_encoders/models/MLP.py
soco_encoders/models/Pooling.py
soco_encoders/models/RoBERTa.py
soco_encoders/models/WordEmbeddings.py
soco_encoders/models/WordWeights.py
soco_encoders/models/XLNet.py
soco_encoders/models/__init__.py
soco_encoders/models/module_bases.py
soco_encoders/models/tokenizer/PhraseTokenizer.py
soco_encoders/models/tokenizer/SocoBertTokenizer.py
soco_encoders/models/tokenizer/WhitespaceTokenizer.py
soco_encoders/models/tokenizer/WordTokenizer.py
soco_encoders/models/tokenizer/__init__.py
soco_encoders/readers/InputExample.py
soco_encoders/readers/LabelSentenceReader.py
soco_encoders/readers/NLIDataReader.py
soco_encoders/readers/STSDataReader.py
soco_encoders/readers/TripletReader.py
soco_encoders/readers/__init__.py
soco_encoders-0.2.9.dist-info/LICENSE
soco_encoders-0.2.9.dist-info/METADATA
soco_encoders-0.2.9.dist-info/WHEEL
soco_encoders-0.2.9.dist-info/top_level.txt
soco_encoders-0.2.9.dist-info/RECORD
